foliant/cli/meta/__init__.py
foliant/cli/meta/meta.py
foliant/meta/__init__.py
foliant/meta/classes.py
foliant/meta/generate.py
foliant/meta/patterns.py
foliant/meta/tools.py
foliant/meta_commands/__init__.py
foliant/meta_commands/base.py
foliant/meta_commands/generate/__init__.py
foliant/meta_commands/generate/command.py
foliantcontrib.meta-1.3.3.dist-info/LICENSE
foliantcontrib.meta-1.3.3.dist-info/METADATA
foliantcontrib.meta-1.3.3.dist-info/WHEEL
foliantcontrib.meta-1.3.3.dist-info/top_level.txt
foliantcontrib.meta-1.3.3.dist-info/RECORD
